Metadata-Version: 1.0
Name: authentic2-auth-kerberos
Version: 1.1.0
Summary: Authentic2 Auth Kerberos
Home-page: UNKNOWN
Author: Entr'ouvert
Author-email: info@entrouvert.com
License: AGPLv3
Platform: UNKNOWN
